SLKB/__init__.py
SLKB/files/.DS_Store
SLKB/files/GEMINI.R
SLKB/files/SLKB_mysql_schema.sql
SLKB/files/SLKB_sqlite3_schema.sql
SLKB/files/SLKB_webapp.zip
SLKB/files/demo_data.pickle
SLKB/files/mageck_control.txt
SLKB/files/pipeline.ipynb
SLKB-1.0.11.dist-info/LICENSE
SLKB-1.0.11.dist-info/METADATA
SLKB-1.0.11.dist-info/WHEEL
SLKB-1.0.11.dist-info/top_level.txt
SLKB-1.0.11.dist-info/RECORD
